rulebase_symbols_detector/__init__.py
rulebase_symbols_detector/init_data.json
rulebase_symbols_detector/init_data.py
rulebase_symbols_detector/question_symbol_detector.py
rulebase_symbols_detector/symbol_detector.py
rulebase_symbols_detector-1.0.0.dist-info/METADATA
rulebase_symbols_detector-1.0.0.dist-info/WHEEL
rulebase_symbols_detector-1.0.0.dist-info/RECORD
