Metadata-Version: 2.3
Name: rulebase_symbols_detector
Version: 1.0.0
Summary: question symbol detector
License: MIT
Author: bachtran
Author-email: tranxuanbach1412@gmail.com
Requires-Python: >=3.8,<4.0
Classifier: License :: OSI Approved :: MIT License
Classifier: Programming Language :: Python :: 3
Classifier: Programming Language :: Python :: 3.8
Classifier: Programming Language :: Python :: 3.9
Classifier: Programming Language :: Python :: 3.10
Classifier: Programming Language :: Python :: 3.11
Classifier: Programming Language :: Python :: 3.12
Classifier: Programming Language :: Python :: 3.13
Requires-Dist: pyvi (==0.1.1)
Requires-Dist: underthesea (==6.3.0)
